rockphypy/AVO.py
rockphypy/Anisotropy.py
rockphypy/BW.py
rockphypy/EM.py
rockphypy/Emp.py
rockphypy/Fluid.py
rockphypy/GM.py
rockphypy/Perm.py
rockphypy/QI.py
rockphypy/__init__.py
rockphypy/utils.py
rockphypy-0.0.2.dist-info/LICENSE
rockphypy-0.0.2.dist-info/METADATA
rockphypy-0.0.2.dist-info/WHEEL
rockphypy-0.0.2.dist-info/top_level.txt
rockphypy-0.0.2.dist-info/RECORD
