Metadata-Version: 2.1
Name: rockphypy
Version: 0.0.2
Summary: Python rock physics toolbox  
Home-page: UNKNOWN
Author: Jiaxin Yu
Author-email: yujiaxin666@outlook.com
License: GNU GPLv3
Platform: UNKNOWN
Classifier: License :: OSI Approved :: GNU General Public License v3 (GPLv3)
Classifier: Programming Language :: Python
Classifier: Programming Language :: Python :: 3
Classifier: Programming Language :: Python :: 3.6
Classifier: Programming Language :: Python :: 3.7
Classifier: Programming Language :: Python :: 3.8
Classifier: Programming Language :: Python :: 3.9
Classifier: Programming Language :: Python :: 3.10
Classifier: Programming Language :: Python :: 3.11
Requires-Dist: numpy (>=1.14.2)
Requires-Dist: scipy (>=1.0.1)
Requires-Dist: matplotlib (>=2.2.0)
Requires-Dist: pandas (>=1.1.1)
Requires-Dist: KDE-diffusion (>=1.0.4)
